package1/__init__.py
package2/__init__.py
package3/__init__.py
MyPackeage_879-0.0.0.dist-info/METADATA
MyPackeage_879-0.0.0.dist-info/WHEEL
MyPackeage_879-0.0.0.dist-info/top_level.txt
MyPackeage_879-0.0.0.dist-info/RECORD
